monedadigitag/__init__.py
monedadigitag-3.0.0.dist-info/METADATA
monedadigitag-3.0.0.dist-info/WHEEL
monedadigitag-3.0.0.dist-info/top_level.txt
monedadigitag-3.0.0.dist-info/RECORD
