Metadata-Version: 2.1
Name: monedadigitag
Version: 3.0.0
Summary: API client for Gemini
Home-page: https://github.com/jvergnol/TSGemini
Author: Julien Vergnol
Author-email: jvergnol@gmail.com
License: GNU GPL
Platform: UNKNOWN
